summarize_requirements.py
summarize_requirements-0.0.1.dist-info/LICENSE
summarize_requirements-0.0.1.dist-info/METADATA
summarize_requirements-0.0.1.dist-info/WHEEL
summarize_requirements-0.0.1.dist-info/top_level.txt
summarize_requirements-0.0.1.dist-info/RECORD
