Metadata-Version: 2.1
Name: summarize-requirements
Version: 0.0.1
Summary: Annotate your requirements.txt file with a short summary of each package.
Home-page: https://github.com/zeke/summarize-python-requirements
Author: Zeke Sikelianos
Author-email: zeke@sikelianos.com
License: UNKNOWN
Platform: UNKNOWN
Classifier: Environment :: Console
Classifier: License :: OSI Approved :: MIT License
Classifier: Programming Language :: Python :: 3
Classifier: Programming Language :: Python :: Implementation :: PyPy
Classifier: Programming Language :: Python
Classifier: Topic :: Documentation
Classifier: Topic :: Software Development :: Documentation
Classifier: Topic :: Software Development :: Libraries :: Python Modules
Requires-Dist: requests (==2.26.0)
Requires-Dist: requirements-parser (==0.2.0)
Provides-Extra: dev
Requires-Dist: check-manifest (>=0.47) ; extra == 'dev'
Requires-Dist: pytest (>=3.7) ; extra == 'dev'
